sixauth/__init__.py
sixauth/auth.py
sixauth/main.py
sixauth/logs/__init__.py
sixauth/logs/log_class.py
sixauth-1.0.2.dist-info/LICENSE
sixauth-1.0.2.dist-info/METADATA
sixauth-1.0.2.dist-info/WHEEL
sixauth-1.0.2.dist-info/top_level.txt
sixauth-1.0.2.dist-info/RECORD
